setup.py
brynq_sdk_sap/__init__.py
brynq_sdk_sap/delimit_endpoints.py
brynq_sdk_sap/post_endpoints.py
brynq_sdk_sap/sap.py
brynq_sdk_sap.egg-info/PKG-INFO
brynq_sdk_sap.egg-info/SOURCES.txt
brynq_sdk_sap.egg-info/dependency_links.txt
brynq_sdk_sap.egg-info/not-zip-safe
brynq_sdk_sap.egg-info/requires.txt
brynq_sdk_sap.egg-info/top_level.txt