Metadata-Version: 1.0
Name: brynq-sdk-sap
Version: 3.0.0
Summary: SAP wrapper from BrynQ
Home-page: UNKNOWN
Author: BrynQ
Author-email: support@brynq.com
License: BrynQ License
Platform: UNKNOWN
